easyuiautomator/__init__.py
easyuiautomator/common/__init__.py
easyuiautomator/common/blackCheck.py
easyuiautomator/common/exceptions.py
easyuiautomator/common/find_img.py
easyuiautomator/common/ftpDownload.py
easyuiautomator/common/log.py
easyuiautomator/common/view_remote_resource.py
easyuiautomator/driver/__init__.py
easyuiautomator/driver/driver.py
easyuiautomator/driver/element.py
easyuiautomator/driver/common/__init__.py
easyuiautomator/driver/common/by.py
easyuiautomator/driver/common/errorCode.py
easyuiautomator/driver/common/keyevent.py
easyuiautomator/driver/common/mobilecommand.py
easyuiautomator/driver/common/multi_action.py
easyuiautomator/driver/common/setting_action.py
easyuiautomator/driver/common/touch_action.py
easyuiautomator/driver/executor/__init__.py
easyuiautomator/driver/executor/adb.py
easyuiautomator/driver/executor/command_executor.py
easyuiautomator/driver/executor/uiautomator.py
easyuiautomator/driver/executor/utils.py
easyuiautomator/driver/executor/wait.py
easyuiautomator/resource/u1/YepTelecomBootstrap.jar
easyuiautomator/resource/u2/testguard-uiautomator-test.apk
easyuiautomator/resource/u2/testguard-uiautomator.apk
easyuiautomator-1.8.4.data/data/Lib/site-packages/cv2.pyd
easyuiautomator-1.8.4.dist-info/METADATA
easyuiautomator-1.8.4.dist-info/WHEEL
easyuiautomator-1.8.4.dist-info/top_level.txt
easyuiautomator-1.8.4.dist-info/RECORD
