Metadata-Version: 2.1
Name: easyuiautomator
Version: 1.8.4
Summary: UNKNOWN
Home-page: UNKNOWN
Author: thomas.ning
Author-email: ningruhu@163.com
License: MIT
Keywords: testing,android,uiautomator
Platform: any
Requires-Dist: requests (>=2.18.1)
